{
  "best_params": {
    "subsample": 1.0,
    "reg_lambda": 5,
    "reg_alpha": 0.01,
    "n_estimators": 200,
    "min_child_weight": 5,
    "max_depth": 8,
    "learning_rate": 0.1,
    "gamma": 0.1,
    "colsample_bytree": 0.8
  },
  "feature_names": [
    "defteam_score",
    "defteam_timeouts_remaining",
    "div_game",
    "down",
    "drive_first_downs",
    "drive_play_count",
    "game_half",
    "game_seconds_remaining",
    "goal_to_go",
    "half_seconds_remaining",
    "location",
    "posteam_score",
    "posteam_timeouts_remaining",
    "qtr",
    "quarter_seconds_remaining",
    "roof",
    "score_differential",
    "side_of_field",
    "spread_line",
    "surface",
    "temp",
    "total_line",
    "wind",
    "yardline_100",
    "ydsnet",
    "ydstogo"
  ],
  "n_features": 26,
  "model_type": "XGBoost Run vs Pass Prediction",
  "target_encoding": {
    "0": "Run",
    "1": "Pass"
  },
  "performance_metrics": {
    "auc_score": 0.784056155533918,
    "classification_report": {
      "0": {
        "precision": 0.6416677055691108,
        "recall": 0.653243645066541,
        "f1-score": 0.6474039334070061,
        "support": 55154.0
      },
      "1": {
        "precision": 0.7544172787508346,
        "recall": 0.7448998998364418,
        "f1-score": 0.7496283820423996,
        "support": 78871.0
      },
      "accuracy": 0.7071814959895542,
      "macro avg": {
        "precision": 0.6980424921599727,
        "recall": 0.6990717724514914,
        "f1-score": 0.6985161577247028,
        "support": 134025.0
      },
      "weighted avg": {
        "precision": 0.7080185474748428,
        "recall": 0.7071814959895542,
        "f1-score": 0.7075609525327075,
        "support": 134025.0
      }
    }
  }
}