{
  "continuous_year": {
    "model": "WAR = b0 + b1(Aggression) + b2(Year) + b3(Aggression x Year)",
    "n_obs": 606,
    "n_clusters": 123,
    "r_squared": 0.03969755685717857,
    "coefficients": {
      "intercept": {
        "beta": -0.06250186117485294,
        "se": 0.10998427233982291,
        "t": -0.5682799899038145,
        "p": 0.5709156522281638
      },
      "aggression": {
        "beta": 17.156147681385818,
        "se": 5.377326259772635,
        "t": 3.1904606216159217,
        "p": 0.0018164433573479855,
        "interpretation": "Main effect of aggression at year 2015"
      },
      "year": {
        "beta": 0.01540474916319835,
        "se": 0.01940358404431025,
        "t": 0.793912564195351,
        "p": 0.4288266329203392,
        "interpretation": "Temporal trend in WAR"
      },
      "aggression_x_year": {
        "beta": -0.8842605530530243,
        "se": 0.7443097680671015,
        "t": -1.1880276075770995,
        "p": 0.237188253383537,
        "interpretation": "Change in aggression effect per year"
      }
    },
    "implied_effects_by_year": {
      "2006": {
        "effect_size": 25.114492658863036,
        "se": 9.827428571150707,
        "t": 2.555550770685718,
        "p": 0.011861932830857791
      },
      "2011": {
        "effect_size": 20.693189893597914,
        "se": 6.92156157921077,
        "t": 2.9896707060659358,
        "p": 0.003394172220649194
      },
      "2017": {
        "effect_size": 15.38762657527977,
        "se": 5.10562567945775,
        "t": 3.0138571727244274,
        "p": 0.003152770814361494
      },
      "2024": {
        "effect_size": 9.1978027039086,
        "se": 7.1414593804843625,
        "t": 1.287944412180465,
        "p": 0.20026419354454972
      }
    }
  },
  "structural_breaks": {
    "2009": {
      "breakpoint": 2009,
      "n_early": 126,
      "n_late": 480,
      "beta_early": 27.42182303678265,
      "beta_late": 17.185469785750456,
      "change": -10.236353251032195,
      "pct_change": -37.329222193949384,
      "rss_pooled": 2142.523405777475,
      "rss_early": 395.7080090512374,
      "rss_late": 1742.7527038785402,
      "f_statistic": 0.5718461600735338,
      "p_value": 0.5647886749841773,
      "reject_null": false
    },
    "2010": {
      "breakpoint": 2010,
      "n_early": 158,
      "n_late": 448,
      "beta_early": 25.545049139657245,
      "beta_late": 16.461597222120652,
      "change": -9.083451917536593,
      "pct_change": -35.55856114379145,
      "rss_pooled": 2142.523405777475,
      "rss_early": 540.9463896933241,
      "rss_late": 1598.6387450014681,
      "f_statistic": 0.4133603199733212,
      "p_value": 0.6616115036889028,
      "reject_null": false
    },
    "2011": {
      "breakpoint": 2011,
      "n_early": 190,
      "n_late": 416,
      "beta_early": 28.737831529936354,
      "beta_late": 11.965935554128245,
      "change": -16.771895975808107,
      "pct_change": -58.36173114988419,
      "rss_pooled": 2142.523405777475,
      "rss_early": 684.4829026903467,
      "rss_late": 1439.2573062617744,
      "f_statistic": 2.6621628298035502,
      "p_value": 0.07061877906198544,
      "reject_null": false
    },
    "2012": {
      "breakpoint": 2012,
      "n_early": 222,
      "n_late": 384,
      "beta_early": 27.188449609915445,
      "beta_late": 10.735114404270709,
      "change": -16.453335205644734,
      "pct_change": -60.51590083917221,
      "rss_pooled": 2142.523405777475,
      "rss_early": 783.6118226802639,
      "rss_late": 1334.9029664462842,
      "f_statistic": 3.411160332238506,
      "p_value": 0.03364212734602512,
      "reject_null": true
    },
    "2013": {
      "breakpoint": 2013,
      "n_early": 254,
      "n_late": 352,
      "beta_early": 26.91019173972311,
      "beta_late": 10.176078022498462,
      "change": -16.73411371722465,
      "pct_change": -62.18504081679513,
      "rss_pooled": 2142.523405777475,
      "rss_early": 907.9837707311093,
      "rss_late": 1211.409119833344,
      "f_statistic": 3.285037479419531,
      "p_value": 0.03811143861162192,
      "reject_null": true
    },
    "2014": {
      "breakpoint": 2014,
      "n_early": 286,
      "n_late": 320,
      "beta_early": 24.487986365907965,
      "beta_late": 10.834239277422752,
      "change": -13.653747088485213,
      "pct_change": -55.75692049344605,
      "rss_pooled": 2142.523405777475,
      "rss_early": 1015.4859099842181,
      "rss_late": 1111.186928996614,
      "f_statistic": 2.2434201059698116,
      "p_value": 0.10698131765796004,
      "reject_null": false
    },
    "2015": {
      "breakpoint": 2015,
      "n_early": 318,
      "n_late": 288,
      "beta_early": 23.472234900035144,
      "beta_late": 10.424358045114396,
      "change": -13.047876854920748,
      "pct_change": -55.588557759794796,
      "rss_pooled": 2142.523405777475,
      "rss_early": 1122.4912734314285,
      "rss_late": 1007.2152612713197,
      "f_statistic": 1.8114599972485073,
      "p_value": 0.16430497758922602,
      "reject_null": false
    },
    "2016": {
      "breakpoint": 2016,
      "n_early": 350,
      "n_late": 256,
      "beta_early": 21.42789514298243,
      "beta_late": 10.748782032829634,
      "change": -10.679113110152795,
      "pct_change": -49.83743404984027,
      "rss_pooled": 2142.523405777475,
      "rss_early": 1265.464238045693,
      "rss_late": 865.3631921190658,
      "f_statistic": 1.6521697672886488,
      "p_value": 0.19250137843864246,
      "reject_null": false
    },
    "2017": {
      "breakpoint": 2017,
      "n_early": 382,
      "n_late": 224,
      "beta_early": 22.460026207679274,
      "beta_late": 9.34761580223258,
      "change": -13.112410405446694,
      "pct_change": -58.381100200869085,
      "rss_pooled": 2142.523405777475,
      "rss_early": 1392.9059955689552,
      "rss_late": 738.8520545858946,
      "f_statistic": 1.5200468187160197,
      "p_value": 0.21953983519676457,
      "reject_null": false
    },
    "2018": {
      "breakpoint": 2018,
      "n_early": 414,
      "n_late": 192,
      "beta_early": 20.069938550948493,
      "beta_late": 11.095657141676536,
      "change": -8.974281409271956,
      "pct_change": -44.71504178495772,
      "rss_pooled": 2142.523405777475,
      "rss_early": 1487.8709756178987,
      "rss_late": 648.3414903847943,
      "f_statistic": 0.8892340544028197,
      "p_value": 0.4115095222795956,
      "reject_null": false
    },
    "2019": {
      "breakpoint": 2019,
      "n_early": 446,
      "n_late": 160,
      "beta_early": 19.07375849728481,
      "beta_late": 13.328808692916072,
      "change": -5.744949804368739,
      "pct_change": -30.11965263787179,
      "rss_pooled": 2142.523405777475,
      "rss_early": 1612.3986736772194,
      "rss_late": 527.4616966472756,
      "f_statistic": 0.37459157731182335,
      "p_value": 0.6877301906455949,
      "reject_null": false
    },
    "best_breakpoint": {
      "year": 2012,
      "p_value": 0.03364212734602512,
      "f_statistic": 3.411160332238506,
      "beta_early": 27.188449609915445,
      "beta_late": 10.735114404270709,
      "change_pct": -60.51590083917221
    }
  }
}